pynubls-0.1.0.dist-info/METADATA
pynubls-0.1.0.dist-info/WHEEL
pynubls/__pycache__/__init__.cpython-38.pyc
pynubls/__init__.py
pynubls/pynubls.cpython-38-x86_64-linux-gnu.so
pynubls-0.1.0.dist-info/RECORD
