Metadata-Version: 2.1
Name: pynubls
Version: 0.1.0
Requires-Dist: py_ecc==5.0.0
Author: NuCypher
